IP5100/__init__.py
IP5100/aspeed.py
IP5100/ip5100.py
ip5100_wrapper-1.0.2.dist-info/licenses/LICENSE
ip5100_wrapper-1.0.2.dist-info/METADATA
ip5100_wrapper-1.0.2.dist-info/WHEEL
ip5100_wrapper-1.0.2.dist-info/top_level.txt
ip5100_wrapper-1.0.2.dist-info/RECORD
