Metadata-Version: 2.4
Name: ip5100-wrapper
Version: 1.0.2
Summary: A Python wrapper for controlling IP5100 ASpeed encoders and decoders via Telnet
Home-page: https://github.com/JFaulk1434/wrapper_IP5100
Author: Justin Faulk
Author-email: Justin Faulk <jfaulk@proitav.us>
License: MIT
Project-URL: Homepage, https://github.com/JFaulk1434/wrapper_IP5100
Project-URL: Bug Tracker, https://github.com/JFaulk143/wrapper_IP5100/issues
Requires-Python: >=3.13
License-File: LICENSE
Requires-Dist: telnetlib-313-and-up
Dynamic: author
Dynamic: home-page
Dynamic: license-file
Dynamic: requires-python
